MANIFEST.in
README.md
VERSION
setup.py
mapactionpy_arcpro/__init__.py
mapactionpy_arcpro/arcpro_runner.py
mapactionpy_arcpro/go.py
mapactionpy_arcpro/map_chef.py
mapactionpy_arcpro/toolbox.py
mapactionpy_arcpro.egg-info/PKG-INFO
mapactionpy_arcpro.egg-info/SOURCES.txt
mapactionpy_arcpro.egg-info/dependency_links.txt
mapactionpy_arcpro.egg-info/not-zip-safe
mapactionpy_arcpro.egg-info/requires.txt
mapactionpy_arcpro.egg-info/top_level.txt
mapactionpy_arcpro/tests/__init__.py
mapactionpy_arcpro/tests/fixtures.py
mapactionpy_arcpro/tests/test_map_chef.py
mapactionpy_arcpro/tests/test_mapactionpy_arcmap.py