Metadata-Version: 2.1
Name: mapactionpy-arcpro
Version: 1.0.0.dev58
Summary: Used to drive ArcGIS Pro
Home-page: http://github.com/mapaction/mapactionpy_arcpro
Author: MapAction
Author-email: github@mapaction.com
License: GPL3
Platform: UNKNOWN
Classifier: Development Status :: 5 - Production/Stable
Classifier: Programming Language :: Python :: 3.6
Classifier: License :: OSI Approved :: GNU General Public License v3 (GPLv3)
Classifier: Operating System :: Microsoft :: Windows
